[{"match_name":"ENPS May 2018 USPSA Match","match_date":"2018-05-06","stage_classifiercode":"06-09","member_number":"A63276","first_name":"ARDENA","last_name":"MRASEK","classification":"U","division":"REVOLVER","hit_factor":2.5021},{"match_name":"MCRC USPSA January 2017","match_date":"2017-01-14","stage_classifiercode":"06-09","member_number":"TY4747","first_name":"MICHAEL","last_name":"WINGARD","classification":"C","division":"REVOLVER","hit_factor":1.5732},{"match_name":"ENPS May 2018 USPSA Match","match_date":"2018-05-06","stage_classifiercode":"06-09","member_number":"TY13098","first_name":"DAVD","last_name":"HINELINE","classification":"U","division":"REVOLVER","hit_factor":1.4706}]