[{"match_name":"ENPS May 2018 USPSA Match","match_date":"2018-05-06","stage_classifiercode":"06-09","member_number":"L3232","first_name":"THOMAS","last_name":"HOWARD","classification":"A","division":"SINGLE STACK","hit_factor":8.4507},{"match_name":"Idaho ISPS May 6th 2018","match_date":"2018-05-06","stage_classifiercode":"06-09","member_number":"TY84532","first_name":"KENNY","last_name":"PLATT","classification":"G","division":"SINGLE STACK","hit_factor":6.6225},{"match_name":"ENPS May 2018 USPSA Match","match_date":"2018-05-06","stage_classifiercode":"06-09","member_number":"L504","first_name":"GARY","last_name":"PENNINGTON","classification":"U","division":"SINGLE STACK","hit_factor":5.4845},{"match_name":"MCRC USPSA January 2017","match_date":"2017-01-14","stage_classifiercode":"06-09","member_number":"TY53092","first_name":"DEWEY","last_name":"HUTSON","classification":"A","division":"SINGLE STACK","hit_factor":5.0847},{"match_name":"Oregon ARPC December 2015 USPSA ","match_date":"2015-12-12","stage_classifiercode":"06-09","member_number":"a74268","first_name":"AARON","last_name":"AVON","classification":"U","division":"SINGLE STACK","hit_factor":4.9751},{"match_name":"Custer December USPSA","match_date":"2016-12-04","stage_classifiercode":"06-09","member_number":"A91246","first_name":"JAMES","last_name":"STEWARD","classification":"D","division":"SINGLE STACK","hit_factor":4.7695},{"match_name":"ENPS May 2018 USPSA Match","match_date":"2018-05-06","stage_classifiercode":"06-09","member_number":"TY7587","first_name":"JOHN","last_name":"VICTOR","classification":"B","division":"SINGLE STACK","hit_factor":4.6802},{"match_name":"Idaho ISPS July 16th Beat the Heat Classifier Match","match_date":"2017-07-16","stage_classifiercode":"06-09","member_number":"A50507","first_name":"JOHN","last_name":"HART","classification":"C","division":"SINGLE STACK","hit_factor":4.4776},{"match_name":"ENPS May 2018 USPSA Match","match_date":"2018-05-06","stage_classifiercode":"06-09","member_number":"A101521","first_name":"JEFF","last_name":"KING","classification":"U","division":"SINGLE STACK","hit_factor":4.0107},{"match_name":"Idaho ISPS July 16th Beat the Heat Classifier Match","match_date":"2017-07-16","stage_classifiercode":"06-09","member_number":"A97864","first_name":"JAMES","last_name":"DERRICK","classification":"C","division":"SINGLE STACK","hit_factor":3.9318},{"match_name":"MCRC USPSA January 2017","match_date":"2017-01-14","stage_classifiercode":"06-09","member_number":"TY73390","first_name":"TUDOR","last_name":"STURZU","classification":"B","division":"SINGLE STACK","hit_factor":3.8511},{"match_name":"Idaho ISPS May 6th 2018","match_date":"2018-05-06","stage_classifiercode":"06-09","member_number":"TY81732","first_name":"JERRY","last_name":"CARBONE","classification":"B","division":"SINGLE STACK","hit_factor":3.8168},{"match_name":"Idaho ISPS July 16th Beat the Heat Classifier Match","match_date":"2017-07-16","stage_classifiercode":"06-09","member_number":"A75553","first_name":"MARK","last_name":"WEAVER","classification":"M","division":"SINGLE STACK","hit_factor":3.7879},{"match_name":"CPS USPSA Mar 2018","match_date":"2018-03-03","stage_classifiercode":"06-09","member_number":"A96958","first_name":"JERRY","last_name":"CAVASSO","classification":"U","division":"SINGLE STACK","hit_factor":3.7083},{"match_name":"Oregon ARPC December 2015 USPSA ","match_date":"2015-12-12","stage_classifiercode":"06-09","member_number":"A59547","first_name":"STEVE","last_name":"KENDELL","classification":"C","division":"SINGLE STACK","hit_factor":3.5211},{"match_name":"ENPS May 2018 USPSA Match","match_date":"2018-05-06","stage_classifiercode":"06-09","member_number":"A85714","first_name":"MONTE","last_name":"SCOBBA","classification":"C","division":"SINGLE STACK","hit_factor":3.4642},{"match_name":"Oregon ARPC December 2015 USPSA ","match_date":"2015-12-12","stage_classifiercode":"06-09","member_number":"TY45897","first_name":"LAWRENCE","last_name":"MULL","classification":"C","division":"SINGLE STACK","hit_factor":3.4286},{"match_name":"BGSL USPSA 5-21 all steel match","match_date":"2017-05-21","stage_classifiercode":"06-09","member_number":"\"\"","first_name":"JOSH","last_name":"BALLARD","classification":"X","division":"SINGLE STACK","hit_factor":3.3149},{"match_name":"BGSL USPSA 5-21 all steel match","match_date":"2017-05-21","stage_classifiercode":"06-09","member_number":"\"\"","first_name":"JIM","last_name":"RIGGS","classification":"U","division":"SINGLE STACK","hit_factor":3.2432},{"match_name":"Idaho ISPS May 6th 2018","match_date":"2018-05-06","stage_classifiercode":"06-09","member_number":"TY97864","first_name":"JAMES","last_name":"DERRICK","classification":"C","division":"SINGLE STACK","hit_factor":3.1646},{"match_name":"MCRC USPSA January 2017","match_date":"2017-01-14","stage_classifiercode":"06-09","member_number":"L3015","first_name":"JOE","last_name":"HORNE","classification":"C","division":"SINGLE STACK","hit_factor":3.1185},{"match_name":"ENPS May 2018 USPSA Match","match_date":"2018-05-06","stage_classifiercode":"06-09","member_number":"FY91514","first_name":"CHASE","last_name":"CEJKA","classification":"U","division":"SINGLE STACK","hit_factor":2.893},{"match_name":"ENPS May 2018 USPSA Match","match_date":"2018-05-06","stage_classifiercode":"06-09","member_number":"FY81857","first_name":"MATT","last_name":"MADDEN","classification":"C","division":"SINGLE STACK","hit_factor":2.7985},{"match_name":"MCRC USPSA January 2017","match_date":"2017-01-14","stage_classifiercode":"06-09","member_number":"A96880","first_name":"JOE","last_name":"MAGAGNOLI","classification":"U","division":"SINGLE STACK","hit_factor":2.7523},{"match_name":"Idaho ISPS May 6th 2018","match_date":"2018-05-06","stage_classifiercode":"06-09","member_number":"\"\"","first_name":"TIM","last_name":"NEWCOMB","classification":"U","division":"SINGLE STACK","hit_factor":2.6224},{"match_name":"ENPS May 2018 USPSA Match","match_date":"2018-05-06","stage_classifiercode":"06-09","member_number":"A103752","first_name":"BILL","last_name":"NEWMAN","classification":"U","division":"SINGLE STACK","hit_factor":2.4691},{"match_name":"ENPS May 2018 USPSA Match","match_date":"2018-05-06","stage_classifiercode":"06-09","member_number":"A106055","first_name":"JOE","last_name":"BROCKELSBY","classification":"U","division":"SINGLE STACK","hit_factor":2.4233},{"match_name":"Oregon ARPC December 2015 USPSA ","match_date":"2015-12-12","stage_classifiercode":"06-09","member_number":"a91567","first_name":"ADAM","last_name":"BELFUS","classification":"C","division":"SINGLE STACK","hit_factor":2.3548},{"match_name":"SAPSC Monthly USPSA Classifier Match at ARO 20160317","match_date":"2016-03-17","stage_classifiercode":"06-09","member_number":"A94737","first_name":"JASON","last_name":"KANNER","classification":"U","division":"SINGLE STACK","hit_factor":2.1614},{"match_name":"ENPS May 2018 USPSA Match","match_date":"2018-05-06","stage_classifiercode":"06-09","member_number":"A90551","first_name":"DAVE","last_name":"BREEDING","classification":"C","division":"SINGLE STACK","hit_factor":2.0747},{"match_name":"ENPS May 2018 USPSA Match","match_date":"2018-05-06","stage_classifiercode":"06-09","member_number":"A49306","first_name":"LESLIE","last_name":"NIELSON","classification":"C","division":"SINGLE STACK","hit_factor":1.9355},{"match_name":"MCRC USPSA January 2017","match_date":"2017-01-14","stage_classifiercode":"06-09","member_number":"TY90372","first_name":"CLARK","last_name":"SMITH","classification":"U","division":"SINGLE STACK","hit_factor":1.9011},{"match_name":"Custer December USPSA","match_date":"2016-12-04","stage_classifiercode":"06-09","member_number":"A98214","first_name":"CHRISTOPHER","last_name":"WISE","classification":"U","division":"SINGLE STACK","hit_factor":1.8394},{"match_name":"Idaho ISPS July 16th Beat the Heat Classifier Match","match_date":"2017-07-16","stage_classifiercode":"06-09","member_number":"\"\"","first_name":"JOHN","last_name":"SIEBOLD","classification":"U","division":"SINGLE STACK","hit_factor":1.8371},{"match_name":"ENPS May 2018 USPSA Match","match_date":"2018-05-06","stage_classifiercode":"06-09","member_number":"A100293","first_name":"JAMES","last_name":"SYTEK","classification":"U","division":"SINGLE STACK","hit_factor":1.3724},{"match_name":"ENPS May 2018 USPSA Match","match_date":"2018-05-06","stage_classifiercode":"06-09","member_number":"a109689","first_name":"JESICA","last_name":"TIANGCO","classification":"U","division":"SINGLE STACK","hit_factor":0.8608},{"match_name":"MCRC USPSA January 2017","match_date":"2017-01-14","stage_classifiercode":"06-09","member_number":"A83077","first_name":"ROBERT","last_name":"SCHULTZ","classification":"D","division":"SINGLE STACK","hit_factor":0.8451}]