[{"match_name":"Area 2 Desert Classic Match 2016","match_date":"2016-03-02","stage_classifiercode":"13-09","member_number":"TY58385","first_name":"RICH","last_name":"WOLFE","classification":"G","division":"REVOLVER","hit_factor":6.9474},{"match_name":"ESPS USPSA May 2017","match_date":"2017-05-27","stage_classifiercode":"13-09","member_number":"A71395","first_name":"BILL","last_name":"DUDA","classification":"A","division":"REVOLVER","hit_factor":6.6148},{"match_name":"Area 2 Desert Classic Match 2016","match_date":"2016-03-02","stage_classifiercode":"13-09","member_number":"FY61528","first_name":"SCOTT","last_name":"FOLK","classification":"A","division":"REVOLVER","hit_factor":6.4577},{"match_name":"Area 2 Desert Classic Match 2016","match_date":"2016-03-02","stage_classifiercode":"13-09","member_number":"A80603","first_name":"CALEB","last_name":"HIGBY","classification":"M","division":"REVOLVER","hit_factor":5.9086},{"match_name":"Area 2 Desert Classic Match 2016","match_date":"2016-03-02","stage_classifiercode":"13-09","member_number":"TY26438","first_name":"ALAN","last_name":"JENKINS","classification":"A","division":"REVOLVER","hit_factor":5.8881},{"match_name":"Area 2 Desert Classic Match 2016","match_date":"2016-03-02","stage_classifiercode":"13-09","member_number":"TY20570","first_name":"DANIEL R.","last_name":"FURBEE","classification":"B","division":"REVOLVER","hit_factor":5.1928},{"match_name":"Area 2 Desert Classic Match 2016","match_date":"2016-03-02","stage_classifiercode":"13-09","member_number":"TY81578","first_name":"BRYAN","last_name":"PORTER","classification":"B","division":"REVOLVER","hit_factor":5.175},{"match_name":"Area 2 Desert Classic Match 2016","match_date":"2016-03-02","stage_classifiercode":"13-09","member_number":"L2820","first_name":"KYLE","last_name":"SCHMIDT","classification":"M","division":"REVOLVER","hit_factor":5.1661},{"match_name":"Area 2 Desert Classic Match 2016","match_date":"2016-03-02","stage_classifiercode":"13-09","member_number":"TY88655","first_name":"KEVIN","last_name":"ROGGENKAMP","classification":"B","division":"REVOLVER","hit_factor":4.9505},{"match_name":"Area 2 Desert Classic Match 2016","match_date":"2016-03-02","stage_classifiercode":"13-09","member_number":"TY51084","first_name":"BRET","last_name":"DRAUGHN","classification":"A","division":"REVOLVER","hit_factor":4.8012},{"match_name":"OREGON ARPC CC05 USPSA MAY 12 2018 Classifier Match","match_date":"2018-05-12","stage_classifiercode":"13-09","member_number":"L3893","first_name":"MICHAEL","last_name":"BURGESS","classification":"B","division":"REVOLVER","hit_factor":4.7522},{"match_name":"Cactus USPSA All Classifier July 2016 (John Razo Reload)","match_date":"2016-07-02","stage_classifiercode":"13-09","member_number":"A90472","first_name":"JON","last_name":"RAZO","classification":"U","division":"REVOLVER","hit_factor":4.7518},{"match_name":"CCPL 02272016","match_date":"2016-02-27","stage_classifiercode":"13-09","member_number":"A82880","first_name":"TIM","last_name":"ELLIOTT","classification":"C","division":"REVOLVER","hit_factor":4.4313},{"match_name":"Area 2 Desert Classic Match 2016","match_date":"2016-03-02","stage_classifiercode":"13-09","member_number":"FY34750","first_name":"RUDY","last_name":"WARREN","classification":"B","division":"REVOLVER","hit_factor":4.2583},{"match_name":"Area 2 Desert Classic Match 2016","match_date":"2016-03-02","stage_classifiercode":"13-09","member_number":"A70021","first_name":"DUANE","last_name":"SNIPES","classification":"C","division":"REVOLVER","hit_factor":4.2262},{"match_name":"EWPSA 2018-06","match_date":"2018-06-17","stage_classifiercode":"13-09","member_number":"TY46298","first_name":"GERALD","last_name":"ASHBECK","classification":"A","division":"REVOLVER","hit_factor":4.1353},{"match_name":"Area 2 Desert Classic Match 2016","match_date":"2016-03-02","stage_classifiercode":"13-09","member_number":"TY68566","first_name":"FRANK","last_name":"D'AMATO","classification":"B","division":"REVOLVER","hit_factor":3.8267},{"match_name":"Cactus USPSA All Classifier July 2016","match_date":"2016-07-03","stage_classifiercode":"13-09","member_number":"A86012","first_name":"MICHAEL","last_name":"DEBOLT","classification":"U","division":"REVOLVER","hit_factor":3.7333},{"match_name":"Area 2 Desert Classic Match 2016","match_date":"2016-03-02","stage_classifiercode":"13-09","member_number":"L3484","first_name":"DENNIS","last_name":"PERRIN","classification":"B","division":"REVOLVER","hit_factor":3.733},{"match_name":"Area 2 Desert Classic Match 2016","match_date":"2016-03-02","stage_classifiercode":"13-09","member_number":"TY23657","first_name":"PHIL","last_name":"TORRES","classification":"D","division":"REVOLVER","hit_factor":3.4501},{"match_name":"CCPL 02272016","match_date":"2016-02-27","stage_classifiercode":"13-09","member_number":"TY88655","first_name":"KEVIN","last_name":"ROGGENKAMP","classification":"B","division":"REVOLVER","hit_factor":3.4263},{"match_name":"Area 2 Desert Classic Match 2016","match_date":"2016-03-02","stage_classifiercode":"13-09","member_number":"TY79607","first_name":"MIKE","last_name":"SHAW","classification":"B","division":"REVOLVER","hit_factor":3.183},{"match_name":"CGC 2016-04-09","match_date":"2016-04-09","stage_classifiercode":"13-09","member_number":"TY57303","first_name":"RONALD","last_name":"BROOKS","classification":"B","division":"REVOLVER","hit_factor":2.5885},{"match_name":"Area 2 Desert Classic Match 2016","match_date":"2016-03-02","stage_classifiercode":"13-09","member_number":"TY42587","first_name":"PHIL","last_name":"ARCHDALE","classification":"C","division":"REVOLVER","hit_factor":2.2919},{"match_name":"Area 2 Desert Classic Match 2016","match_date":"2016-03-02","stage_classifiercode":"13-09","member_number":"TY47648","first_name":"JOHN A","last_name":"RODRIGUEZ","classification":"A","division":"REVOLVER","hit_factor":1.994},{"match_name":"Area 2 Desert Classic Match 2016","match_date":"2016-03-02","stage_classifiercode":"13-09","member_number":"A67475","first_name":"MADDY","last_name":"FOLK","classification":"C","division":"REVOLVER","hit_factor":1.731},{"match_name":"CCPL 02272016","match_date":"2016-02-27","stage_classifiercode":"13-09","member_number":"\"\"","first_name":"SHERYL","last_name":"ELLIOTT","classification":"U","division":"REVOLVER","hit_factor":1.4987},{"match_name":"CCPL 02272016","match_date":"2016-02-27","stage_classifiercode":"13-09","member_number":"A88825","first_name":"ED","last_name":"ARAIM","classification":"D","division":"REVOLVER","hit_factor":1.2365},{"match_name":"CCPL 02272016","match_date":"2016-02-27","stage_classifiercode":"13-09","member_number":"TY81578","first_name":"BRYAN","last_name":"PORTER","classification":"B","division":"REVOLVER","hit_factor":0.8327}]